Workbook
Name Slicer_Attrition: #N/A
Name Slicer_Department: #N/A
Name Slicer_Gender: #N/A
Name Slicer_WorkLocation: #N/A

Sheet HR_datas
A1: EmployeeID | B1: EmployeeName | C1: Gender | D1: Age | E1: Department | F1: JobRole | G1: Education | H1: ExperienceYears | I1: Salary | J1: PerformanceRating | K1: Attrition | L1: WorkLocation | M1: JoiningYear
A2: E001 | B2: Aarav | C2: Male | D2: 26 | E2: IT | F2: Software Engineer | G2: Bachelor | H2: 3 | I2: 45000 | J2: 3 | K2: No | L2: Bangalore | M2: 2022
A3: E002 | B3: Diya | C3: Female | D3: 29 | E3: HR | F3: HR Executive | G3: MBA | H3: 6 | I3: 52000 | J3: 4 | K3: No | L3: Chennai | M3: 2019
A4: E003 | B4: Rohan | C4: Male | D4: 35 | E4: Finance | F4: Accountant | G4: Bachelor | H4: 10 | I4: 68000 | J4: 4 | K4: No | L4: Mumbai | M4: 2015
A5: E004 | B5: Ananya | C5: Female | D5: 24 | E5: IT | F5: QA Engineer | G5: Bachelor | H5: 2 | I5: 38000 | J5: 3 | K5: No | L5: Hyderabad | M5: 2023
A6: E005 | B6: Karthik | C6: Male | D6: 41 | E6: Operations | F6: Operations Manager | G6: MBA | H6: 16 | I6: 95000 | J6: 5 | K6: No | L6: Bangalore | M6: 2009
A7: E006 | B7: Priya | C7: Female | D7: 31 | E7: Sales | F7: Sales Executive | G7: Bachelor | H7: 8 | I7: 60000 | J7: 4 | K7: No | L7: Delhi | M7: 2017
A8: E007 | B8: Vikram | C8: Male | D8: 28 | E8: Marketing | F8: Digital Marketer | G8: Bachelor | H8: 5 | I8: 55000 | J8: 3 | K8: Yes | L8: Pune | M8: 2020
A9: E008 | B9: Neha | C9: Female | D9: 34 | E9: HR | F9: HR Manager | G9: MBA | H9: 11 | I9: 78000 | J9: 5 | K9: No | L9: Mumbai | M9: 2014
A10: E009 | B10: Arjun | C10: Male | D10: 23 | E10: IT | F10: Intern | G10: Diploma | H10: 1 | I10: 22000 | J10: 2 | K10: Yes | L10: Bangalore | M10: 2024
A11: E010 | B11: Sneha | C11: Female | D11: 37 | E11: Finance | F11: Finance Manager | G11: MBA | H11: 14 | I11: 98000 | J11: 5 | K11: No | L11: Delhi | M11: 2011
A12: E011 | B12: Rahul | C12: Male | D12: 30 | E12: IT | F12: Software Engineer | G12: Bachelor | H12: 7 | I12: 65000 | J12: 4 | K12: No | L12: Hyderabad | M12: 2018
A13: E012 | B13: Pooja | C13: Female | D13: 27 | E13: Sales | F13: Sales Executive | G13: Bachelor | H13: 4 | I13: 48000 | J13: 3 | K13: Yes | L13: Chennai | M13: 2021
... A301: E300 | B301: Suman | C301: Female | D301: 41 | E301: HR | F301: Global HR Director | G301: MBA | H301: 18 | I301: 135000 | J301: 5 | K301: No | L301: Bangalore | M301: 2007

Sheet Pivot
G1: KPI1 | Y1: KPI3 | AF1: KPI4
B2: kpi | H2: Total Employees by Department. Highlight the department with the max headcount. | L2: Total Employees trend over JoiningYear Which year had the highest recruitment? | P2: Total employees by gender and dept | Z2: Average Salary by Department | AG2: Average Performance Rating by Department
B3: Count of EmployeeID | C3: headcount | AE3: bar chart; mark top 3 and bottom 3 performing departments. | AG3: Row Labels | AH3: Average of PerformanceRating | AQ3: performance rating trend by JoiningYear
B4: 300 | H4: Row Labels | I4: Count of EmployeeID | L4: Row Labels | M4: Count of EmployeeID | Z4: Row Labels | AA4: Average of Salary | AB4: bar chart | AG4: Finance | AH4: 4.2352941
H5: Finance | I5: 51 | L5: 2011-2015 | M5: 72 | P5: Count of EmployeeID | Q5: Column Labels | Z5: Finance | AA5: 90803.922 | AB5: highlight dept. below the company avg | AG5: HR | AH5: 3.745098 | AP5: Row Labels | AQ5: Average of PerformanceRating
B6: Row Labels | C6: Count of Attrition | D6: attrition % | H6: HR | I6: 51 | L6: 2016-2020 | M6: 71 | P6: Row Labels | Q6: Female | R6: Male | S6: Grand Total | Z6: HR | AA6: 66529.412 | AG6: IT | AH6: 3.9333333 | AP6: 1996-2000 | AQ6: 5
B7: No | C7: 0.76666667 | D7: yes | H7: IT | I7: 60 | L7: 2021-2025 | M7: 58 | P7: Finance | Q7: 26 | R7: 25 | S7: 51 | Z7: IT | AA7: 79283.333 | AG7: Marketing | AH7: 3.673913 | AP7: 2001-2005 | AQ7: 5
B8: Yes | C8: 0.23333333 | H8: Marketing | I8: 46 | L8: 2006-2010 | M8: 58 | P8: HR | Q8: 50 | R8: 1 | S8: 51 | Z8: Marketing | AA8: 72347.826 | AG8: Operations | AH8: 4.6511628 | AP8: 2006-2010 | AQ8: 4.7068966
E9: Slicers : | H9: Operations | I9: 43 | L9: 2001-2005 | M9: 29 | P9: IT | Q9: 7 | R9: 53 | S9: 60 | Z9: Operations | AA9: 122488.37 | AG9: Sales | AH9: 3.755102 | AP9: 2011-2015 | AQ9: 4.125
B10: Average of Salary | C10: Average Salary | E10: Department | H10: Sales | I10: 49 | L10: 1996-2000 | M10: 12 | P10: Marketing | Q10: 38 | R10: 8 | S10: 46 | Z10: Sales | AA10: 70469.388 | AG10: Grand Total | AH10: 3.9866667 | AP10: 2016-2020 | AQ10: 3.7042254
B11: 82763.333 | E11: * WorkLocation | H11: Grand Total | I11: 300 | L11: Grand Total | M11: 300 | P11: Operations | Q11: 5 | R11: 38 | S11: 43 | Z11: Grand Total | AA11: 82763.333 | AP11: 2021-2025 | AQ11: 2.7241379
E12: * Gender | P12: Sales | Q12: 24 | R12: 25 | S12: 49 | V12: Average Salary by Gender across Departments | AG12: performance ratings across WorkLocation and Department | AP12: Grand Total | AQ12: 3.9866667
B13: Avg of PerformRating | E13: * Attrition | P13: Grand Total | Q13: 150 | R13: 150 | S13: 300 | Z13: clustered column chart
B14: 3.9866667 | E14: * JoiningYear | V14: Average of Salary | W14: Column Labels | AG14: Average of PerformanceRating | AH14: Column Labels
V15: Row Labels | W15: Finance | X15: HR | Y15: IT | Z15: Marketing | AA15: Operations | AB15: Sales | AC15: Grand Total | AG15: Row Labels | AH15: Finance | AI15: HR | AJ15: IT | AK15: Marketing | AL15: Operations | AM15: Sales | AN15: Grand Total
C16: Female % / Male % | P16: Location wise employees count | V16: Female | W16: 95884.615 | X16: 67060 | Y16: 60285.714 | Z16: 65842.105 | AA16: 93000 | AB16: 63458.333 | AC16: 71720 | AG16: Bangalore | AH16: 4.1666667 | AI16: 4 | AJ16: 3.7222222 | AK16: 3.5384615 | AL16: 4.5384615 | AM16: 3.8 | AN16: 3.9242424
B17: Row Labels | C17: Gender % | P17: Row Labels | Q17: Count of EmployeeID | V17: Male | W17: 85520 | X17: 40000 | Y17: 81792.453 | Z17: 103250 | AA17: 126368.42 | AB17: 77200 | AC17: 93806.667 | AG17: Chennai | AH17: 4.75 | AI17: 4.125 | AJ17: 4.625 | AK17: 3 | AL17: 4.8181818 | AM17: 4.1818182 | AN17: 4.4418605
B18: Female | C18: 0.5 | M18: Total Employees by Attrition Status | P18: Bangalore | Q18: 66 | V18: Grand Total | W18: 90803.922 | X18: 66529.412 | Y18: 79283.333 | Z18: 72347.826 | AA18: 122488.37 | AB18: 70469.388 | AC18: 82763.333 | AG18: Delhi | AH18: 4.4 | AI18: 3.1111111 | AJ18: 3.5 | AK18: 3.5555556 | AL18: 4.5 | AM18: 3.5 | AN18: 3.7659574
B19: Male | C19: 0.5 | P19: Chennai | Q19: 43 | AG19: Hyderabad | AH19: 4.1666667 | AI19: 3.7142857 | AJ19: 3.6 | AK19: 3.3636364 | AL19: 4.1428571 | AM19: 3 | AN19: 3.7021277
B20: Grand Total | C20: 1 | M20: Row Labels | N20: Count of EmployeeID | P20: Delhi | Q20: 47 | AG20: Mumbai | AH20: 4.4545455 | AI20: 4.6 | AJ20: 4.625 | AK20: 4.3636364 | AL20: 5 | AM20: 4.8 | AN20: 4.5882353
M21: No | N21: 230 | P21: Hyderabad | Q21: 47 | Z21: Average Salary by WorkLocation, Department, or JoiningYear | AG21: Pune | AH21: 3.5555556 | AI21: 3.0909091 | AJ21: 3.7777778 | AK21: 3 | AL21: 5 | AM21: 3.1666667 | AN21: 3.5
M22: Yes | N22: 70 | P22: Mumbai | Q22: 51 | AG22: Grand Total | AH22: 4.2352941 | AI22: 3.745098 | AJ22: 3.9333333 | AK22: 3.673913 | AL22: 4.6511628 | AM22: 3.755102 | AN22: 3.9866667
M23: Grand Total | N23: 300 | P23: Pune | Q23: 46 | AG23: Conditional Formatting → Color Scale
P24: Grand Total | Q24: 300
A25: KPI2 | AG25: Performance Rating by Gender
AG26: Count of Gender | AH26: Column Labels
A27: yearly attrition rate | D27: Attrition Rate by Department | AG27: Row Labels | AH27: Female | AI27: Male | AJ27: Grand Total
AG28: 2 | AH28: 12 | AI28: 5 | AJ28: 17
A29: Row Labels | B29: Count of Attrition | D29: Attrition% | E29: Column Labels | U29: scatter chart | AG29: 3 | AH29: 40 | AI29: 21 | AJ29: 61
A30: 1996-2000 | B30: 0.04 | D30: Row Labels | E30: No | F30: Yes | AG30: 4 | AH30: 64 | AI30: 67 | AJ30: 131
A31: 2001-2005 | B31: 0.096666667 | D31: Finance | E31: 0.90196078 | F31: 0.098039216 | G31: Which dept is riskiest? | AG31: 5 | AH31: 34 | AI31: 57 | AJ31: 91
A32: 2006-2010 | B32: 0.19333333 | D32: HR | E32: 0.56862745 | F32: 0.43137255 | R32: KPI5 | X32: Gender Distribution across WorkLocations | AG32: Grand Total | AH32: 150 | AI32: 150 | AJ32: 300
A33: 2011-2015 | B33: 0.24 | D33: IT | E33: 0.83333333 | F33: 0.16666667 | S33: Gender Distribution by Department
A34: 2016-2020 | B34: 0.23666667 | D34: Marketing | E34: 0.67391304 | F34: 0.32608696 | X34: Count of Gender | Y34: Column Labels
A35: 2021-2025 | B35: 0.19333333 | D35: Operations | E35: 1 | F35: 0 | S35: Count of Gender | T35: Column Labels | X35: Row Labels | Y35: Female | Z35: Male | AG35: Avg of Perform.Rating
D36: Sales | E36: 0.63265306 | F36: 0.36734694 | S36: Row Labels | T36: Female | U36: Male | X36: Bangalore | Y36: 0.39393939 | Z36: 0.60606061 | AA36: *clustered column chart | AH36: Finance | AI36: HR | AJ36: IT | AK36: Marketing | AL36: Operations | AM36: Sales | AN36: Grand Total
S37: Finance | T37: 0.50980392 | U37: 0.49019608 | V37: 100% stacked bar chart | X37: Chennai | Y37: 0.44186047 | Z37: 0.55813953 | AG37: Bangalore | AH37: 4.1666667 | AI37: 4 | AJ37: 3.7222222 | AK37: 3.5384615 | AL37: 4.5384615 | AM37: 3.8 | AN37: 3.9242424
D38: Attrition Rate by WorkLocation | G38: with conditional formatting (color >10% red <5% green) | S38: HR | T38: 0.98039216 | U38: 0.019607843 | X38: Delhi | Y38: 0.57446809 | Z38: 0.42553191 | AG38: Chennai | AH38: 4.75 | AI38: 4.125 | AJ38: 4.625 | AK38: 3 | AL38: 4.8181818 | AM38: 4.1818182 | AN38: 4.4418605
D39: Attrition% | E39: Column Labels | S39: IT | T39: 0.11666667 | U39: 0.88333333 | X39: Hyderabad | Y39: 0.55319149 | Z39: 0.44680851 | AG39: Delhi | AH39: 4.4 | AI39: 3.1111111 | AJ39: 3.5 | AK39: 3.5555556 | AL39: 4.5 | AM39: 3.5 | AN39: 3.7659574
D40: Row Labels | E40: No | F40: Yes | S40: Marketing | T40: 0.82608696 | U40: 0.17391304 | X40: Mumbai | Y40: 0.56862745 | Z40: 0.43137255 | AG40: Hyderabad | AH40: 4.1666667 | AI40: 3.7142857 | AJ40: 3.6 | AK40: 3.3636364 | AL40: 4.1428571 | AM40: 3 | AN40: 3.7021277
D41: Bangalore | E41: 0.81818182 | F41: 0.18181818 | S41: Operations | T41: 0.11627907 | U41: 0.88372093 | X41: Pune | Y41: 0.5 | Z41: 0.5 | AG41: Mumbai | AH41: 4.4545455 | AI41: 4.6 | AJ41: 4.625 | AK41: 4.3636364 | AL41: 5 | AM41: 4.8 | AN41: 4.5882353
D42: Chennai | E42: 0.88372093 | F42: 0.11627907 | S42: Sales | T42: 0.48979592 | U42: 0.51020408 | AG42: Pune | AH42: 3.5555556 | AI42: 3.0909091 | AJ42: 3.7777778 | AK42: 3 | AL42: 5 | AM42: 3.1666667 | AN42: 3.5
D43: Delhi | E43: 0.68085106 | F43: 0.31914894 | AG43: Grand Total | AH43: 4.2352941 | AI43: 3.745098 | AJ43: 3.9333333 | AK43: 3.673913 | AL43: 4.6511628 | AM43: 3.755102 | AN43: 3.9866667
D44: Hyderabad | E44: 0.72340426 | F44: 0.27659574 | S44: Gender Ratio trend over JoiningYear | X44: overall gender ratio and connect slicers for Department & WorkLocation
D45: Mumbai | E45: 0.96078431 | F45: 0.039215686
D46: Pune | E46: 0.5 | F46: 0.5 | S46: Count of Gender | T46: Column Labels
S47: Row Labels | T47: Female | U47: Male | X47: Row Labels | Y47: Count of Gender
S48: 1996-2000 | T48: 0 | U48: 1 | V48: Column / Line Chart | X48: Female | Y48: 0.5 | Z48: donut chart
D49: Attrition Rate by Gender | S49: 2001-2005 | T49: 0.34482759 | U49: 0.65517241 | X49: Male | Y49: 0.5
D50: Count of Attrition | E50: Column Labels | S50: 2006-2010 | T50: 0.43103448 | U50: 0.56896552 | V50: Choose 100% Stacked Column
D51: Row Labels | E51: No | F51: Yes | S51: 2011-2015 | T51: 0.52777778 | U51: 0.47222222 | X51: Departments with <30% Female or Male
D52: Female | E52: 0.68 | F52: 0.32 | G52: pie or donut chart** | S52: 2016-2020 | T52: 0.49295775 | U52: 0.50704225
D53: Male | E53: 0.85333333 | F53: 0.14666667 | S53: 2021-2025 | T53: 0.72413793 | U53: 0.27586207
W55: Count of Gender | X55: Column Labels
W56: Row Labels | X56: Female | Y56: Male
W57: Finance | X57: 0.50980392 | Y57: 0.49019608 | Z57: conditional format or color-coded chart.
D58: showing total employees vs. attrition rate per department. | W58: HR | X58: 0.98039216 | Y58: 0.019607843
W59: IT | X59: 0.11666667 | Y59: 0.88333333
D60: Count of EmployeeID | E60: Column Labels | W60: Marketing | X60: 0.82608696 | Y60: 0.17391304
D61: Row Labels | E61: Yes | W61: Operations | X61: 0.11627907 | Y61: 0.88372093
D62: HR | E62: 0.31428571 | W62: Sales | X62: 0.48979592 | Y62: 0.51020408
D63: Sales | E63: 0.25714286
D64: Marketing | E64: 0.21428571
D65: IT | E65: 0.14285714 | X65: Average Salary vs. Performance Rating
D66: Finance | E66: 0.071428571
D67: Grand Total | E67: 1 | X67: Average of Salary | Y67: Column Labels
X68: Row Labels | Y68: Finance | Z68: HR | AA68: IT | AB68: Marketing | AC68: Operations | AD68: Sales | AE68: Grand Total
X69: 2 | Y69: 28000 | Z69: 25000 | AA69: 25333.333 | AB69: 24666.667 | AD69: 29333.333 | AE69: 26058.824
X70: 3 | Y70: 42666.667 | Z70: 41736.842 | AA70: 46538.462 | AB70: 52888.889 | AD70: 48764.706 | AE70: 46409.836
X71: 4 | Y71: 81407.407 | Z71: 75294.118 | AA71: 76068.966 | AB71: 79680 | AC71: 81800 | AD71: 75888.889 | AE71: 78389.313
X72: 5 | Y72: 118368.42 | Z72: 103750 | AA72: 124666.67 | AB72: 118666.67 | AC72: 144285.71 | AD72: 106363.64 | AE72: 124021.98
X73: Grand Total | Y73: 90803.922 | Z73: 66529.412 | AA73: 79283.333 | AB73: 72347.826 | AC73: 122488.37 | AD73: 70469.388 | AE73: 82763.333
AC75: Row Labels | AD75: Sum of Salary
AC76: Finance | AD76: 4631000
Z77: Salary by Departments | AC77: HR | AD77: 3393000
AC78: IT | AD78: 4757000
AC79: Marketing | AD79: 3328000
AC80: Operations | AD80: 5267000
AC81: Sales | AD81: 3453000
AC82: Grand Total | AD82: 24829000

Sheet Main_Dashboard
A6: =GETPIVOTDATA("EmployeeID",Pivot!$B$3) -> 300
A7: =GETPIVOTDATA("Attrition",Pivot!$B$6,"Attrition","Yes") -> 0.23333333
A8: =GETPIVOTDATA("Salary",Pivot!$B$10) -> 82763.333
A9: =GETPIVOTDATA("PerformanceRating",Pivot!$B$13) -> 3.9866667
A10: =GETPIVOTDATA("Gender",Pivot!$B$17) -> 1

Sheet Head_count
A6: =GETPIVOTDATA("EmployeeID",Pivot!$B$3) -> 300
A7: =GETPIVOTDATA("Attrition",Pivot!$B$6,"Attrition","Yes") -> 0.23333333
A8: =GETPIVOTDATA("Salary",Pivot!$B$10) -> 82763.333
A9: =GETPIVOTDATA("PerformanceRating",Pivot!$B$13) -> 3.9866667
A10: =GETPIVOTDATA("Gender",Pivot!$B$17) -> 1

Sheet Attrition_rate
A6: =GETPIVOTDATA("EmployeeID",Pivot!$B$3) -> 300
A7: =GETPIVOTDATA("Attrition",Pivot!$B$6,"Attrition","Yes") -> 0.23333333
A8: =GETPIVOTDATA("Salary",Pivot!$B$10) -> 82763.333
A9: =GETPIVOTDATA("PerformanceRating",Pivot!$B$13) -> 3.9866667
A10: =GETPIVOTDATA("Gender",Pivot!$B$17) -> 1

Sheet Salary
A6: =GETPIVOTDATA("EmployeeID",Pivot!$B$3) -> 300
A7: =GETPIVOTDATA("Attrition",Pivot!$B$6,"Attrition","Yes") -> 0.23333333
A8: =GETPIVOTDATA("Salary",Pivot!$B$10) -> 82763.333
A9: =GETPIVOTDATA("PerformanceRating",Pivot!$B$13) -> 3.9866667
A10: =GETPIVOTDATA("Gender",Pivot!$B$17) -> 1

Sheet Performance
A6: =GETPIVOTDATA("EmployeeID",Pivot!$B$3) -> 300
A7: =GETPIVOTDATA("Attrition",Pivot!$B$6,"Attrition","Yes") -> 0.23333333
A8: =GETPIVOTDATA("Salary",Pivot!$B$10) -> 82763.333
A9: =GETPIVOTDATA("PerformanceRating",Pivot!$B$13) -> 3.9866667
A10: =GETPIVOTDATA("Gender",Pivot!$B$17) -> 1

Sheet Diversity
A6: =GETPIVOTDATA("EmployeeID",Pivot!$B$3) -> 300
A7: =GETPIVOTDATA("Attrition",Pivot!$B$6,"Attrition","Yes") -> 0.23333333
A8: =GETPIVOTDATA("Salary",Pivot!$B$10) -> 82763.333
A9: =GETPIVOTDATA("PerformanceRating",Pivot!$B$13) -> 3.9866667
A10: =GETPIVOTDATA("Gender",Pivot!$B$17) -> 1
